jaia/__init__.py
jaia/constants.py
jaia/plot.py
jaia/utils.py
jaia-0.0.1.dist-info/LICENSE
jaia-0.0.1.dist-info/METADATA
jaia-0.0.1.dist-info/WHEEL
jaia-0.0.1.dist-info/top_level.txt
jaia-0.0.1.dist-info/RECORD
