Metadata-Version: 2.1
Name: jaia
Version: 0.0.1
Summary: A Jupyter Ab Initio Analalyzer tool with a variety of tools
Home-page: https://github.com/mgamigo/JAIA
Author: Martin Gutierrez-Amigo
Author-email: Martin Gutierrez-Amigo <martin00gutierrez@outlook.com>
Project-URL: Homepage, https://github.com/mgamigo/JAIA
Project-URL: Bug Tracker, https://github.com/mgamigo/JAIA/issues
Classifier: Programming Language :: Python :: 3
Classifier: License :: OSI Approved :: GNU General Public License v3 (GPLv3)
Classifier: Operating System :: OS Independent
Requires-Python: >=3.6
License-File: LICENSE
Requires-Dist: ipympl (==0.9.1)
